tabs_data_download/__init__.py
tabs_data_download/binance/__init__.py
tabs_data_download/binance/trades.py
tabs_data_download/book.py
tabs_data_download/kraken/__init__.py
tabs_data_download/kraken/facilities/__init__.py
tabs_data_download/kraken/facilities/cfRestApiV3.py
tabs_data_download/kraken/trades.py
tabs_data_download/main.py
tabs_data_download/missing_dates.py
tabs_data_download/ticker.py
tabs_data_download/trade.py
tabs_data_download-0.1.4.dist-info/entry_points.txt
tabs_data_download-0.1.4.dist-info/WHEEL
tabs_data_download-0.1.4.dist-info/METADATA
tabs_data_download-0.1.4.dist-info/RECORD
