Metadata-Version: 2.1
Name: tabs-data-download
Version: 0.1.4
License: MIT
Author-email: Alexis Rosuel <rosuelalexis1@gmail.com>
Requires-Python: >=3.11
Requires-Dist: ccxt>=3.0.4
Requires-Dist: tabs-storage>=0.1.3
